pondas/__init__.py
pondas/templates.py
pondas-0.0.2.dist-info/licenses/LICENSE
pondas-0.0.2.dist-info/METADATA
pondas-0.0.2.dist-info/WHEEL
pondas-0.0.2.dist-info/top_level.txt
pondas-0.0.2.dist-info/RECORD
