Metadata-Version: 2.4
Name: pondas
Version: 0.0.2
Summary: ML Examples
Author: Meow Meow
Requires-Python: >=3.8
License-File: LICENSE
Dynamic: license-file
